MANIFEST.in
README.txt
distribute_setup.py
setup.py
Scripts/XSPECfeeder
XSF/__init__.py
XSF/Files/TableRead.py
XSF/Files/TableWrite.py
XSF/Files/__init__.py
XSF/System/Pipe.py
XSF/System/Which.py
XSF/System/__init__.py
XSF/Units/ERGA2JY.py
XSF/Units/ERGH2JY.py
XSF/Units/FL2XSPEC.py
XSF/Units/FLHE2XSPEC.py
XSF/Units/FLMAG2XSPEC.py
XSF/Units/HZ2ANG.py
XSF/Units/NM2ANG.py
XSF/Units/TEV2GEV.py
XSF/Units/__init__.py
XSF/Units/dataCheck.py
XSPECfeeder.egg-info/PKG-INFO
XSPECfeeder.egg-info/SOURCES.txt
XSPECfeeder.egg-info/dependency_links.txt
XSPECfeeder.egg-info/requires.txt
XSPECfeeder.egg-info/top_level.txt