Metadata-Version: 1.0
Name: XSPECfeeder
Version: 0.5.0
Summary: Scientific data management
Home-page: http://www.me.oa-brera.inaf.it/utenti/covino
Author: Jure Japelj, Stefano Covino
Author-email: stefano.covino@brera.inaf.it
License: UNKNOWN
Download-URL: http://www.me.oa-brera.inaf.it/utenti/covino/XSPECfeeder-0.5.0.tar.gz
Platform: UNKNOWN
Classifier: Development Status :: 5 - Production/Stable
Classifier: Environment :: Console
Classifier: Intended Audience :: Science/Research
Classifier: License :: Freely Distributable
Classifier: Operating System :: MacOS :: MacOS X
Classifier: Operating System :: POSIX
Classifier: Programming Language :: Python :: 2
Classifier: Topic :: Scientific/Engineering :: Astronomy
